[{"subject":"NURS","catalog_nbr":364,"section":605,"class_nbr":6359,"title":"NRSG","component":"CARE ADULTS I","units":0,"bldg":"TBA","room":"TBA","days":"Tu","time":"07","instructor":"Staff","load":"100","rank":"INST","attributes":null,"enrl_cap":8,"enrl_tot":8,"wait_cap":0,"wait_tot":0,"prereqs":null,"rmp":null},{"subject":"NURS","catalog_nbr":364,"section":1,"class_nbr":2120,"title":"NRSG","component":"CARE ADULTS I","units":0,"bldg":"TBA","room":"TBA","days":"Th","time":"13","instructor":"PAGE,JULIANNE B","load":"100","rank":"INST","attributes":null,"enrl_cap":109,"enrl_tot":109,"wait_cap":0,"wait_tot":0,"prereqs":null,"rmp":null},{"subject":"NURS","catalog_nbr":364,"section":601,"class_nbr":6355,"title":"NRSG","component":"CARE ADULTS I","units":0,"bldg":"TBA","room":"TBA","days":"TuW","time":"07","instructor":"PAGE,JULIANNE B","load":"100","rank":"INST","attributes":null,"enrl_cap":7,"enrl_tot":7,"wait_cap":0,"wait_tot":0,"prereqs":null,"rmp":null},{"subject":"NURS","catalog_nbr":364,"section":606,"class_nbr":6360,"title":"NRSG","component":"CARE ADULTS I","units":0,"bldg":"TBA","room":"TBA","days":"TuW","time":"07","instructor":"HEISER,THEODORE","load":"100","rank":"INST","attributes":null,"enrl_cap":8,"enrl_tot":7,"wait_cap":0,"wait_tot":0,"prereqs":null,"rmp":null},{"subject":"NURS","catalog_nbr":364,"section":604,"class_nbr":6358,"title":"NRSG","component":"CARE ADULTS I","units":0,"bldg":"TBA","room":"TBA","days":"TuW","time":"07","instructor":"LESTER,VICKIE M","load":"100","rank":"INST","attributes":null,"enrl_cap":8,"enrl_tot":8,"wait_cap":0,"wait_tot":0,"prereqs":null,"rmp":null},{"subject":"NURS","catalog_nbr":364,"section":603,"class_nbr":6357,"title":"NRSG","component":"CARE ADULTS I","units":0,"bldg":"TBA","room":"TBA","days":"TuW","time":"07","instructor":"WILLCOX,ESTHER C","load":"100","rank":"INST","attributes":null,"enrl_cap":8,"enrl_tot":8,"wait_cap":0,"wait_tot":0,"prereqs":null,"rmp":null},{"subject":"NURS","catalog_nbr":364,"section":607,"class_nbr":6361,"title":"NRSG","component":"CARE ADULTS I","units":0,"bldg":"TBA","room":"TBA","days":"TuW","time":"07","instructor":"BANGURA,ABU S","load":"100","rank":"INST","attributes":null,"enrl_cap":8,"enrl_tot":8,"wait_cap":0,"wait_tot":0,"prereqs":null,"rmp":null},{"subject":"NURS","catalog_nbr":364,"section":608,"class_nbr":6362,"title":"NRSG","component":"CARE ADULTS I","units":0,"bldg":"TBA","room":"TBA","days":"M","time":"07","instructor":"Crawford,Catherine M.","load":"100","rank":"INST","attributes":null,"enrl_cap":8,"enrl_tot":8,"wait_cap":0,"wait_tot":0,"prereqs":null,"rmp":null},{"subject":"NURS","catalog_nbr":364,"section":609,"class_nbr":6363,"title":"NRSG","component":"CARE ADULTS I","units":0,"bldg":"TBA","room":"TBA","days":"Tu","time":"07","instructor":"PAGE,JULIANNE B","load":"100","rank":"INST","attributes":null,"enrl_cap":8,"enrl_tot":8,"wait_cap":0,"wait_tot":0,"prereqs":null,"rmp":null},{"subject":"NURS","catalog_nbr":364,"section":610,"class_nbr":6364,"title":"NRSG","component":"CARE ADULTS I","units":0,"bldg":"TBA","room":"TBA","days":"Tu","time":"07","instructor":"PAGE,JULIANNE B","load":"100","rank":"INST","attributes":null,"enrl_cap":8,"enrl_tot":8,"wait_cap":0,"wait_tot":0,"prereqs":null,"rmp":null},{"subject":"NURS","catalog_nbr":364,"section":614,"class_nbr":16546,"title":"NRSG","component":"CARE ADULTS I","units":0,"bldg":"TBA","room":"TBA","days":"Tu","time":"07","instructor":"PAGE,JULIANNE B","load":"100","rank":"INST","attributes":null,"enrl_cap":7,"enrl_tot":7,"wait_cap":0,"wait_tot":0,"prereqs":null,"rmp":null},{"subject":"NURS","catalog_nbr":364,"section":611,"class_nbr":6365,"title":"NRSG","component":"CARE ADULTS I","units":0,"bldg":"TBA","room":"TBA","days":"M","time":"07","instructor":"Johnson,Tarshe","load":"100","rank":"INST","attributes":null,"enrl_cap":8,"enrl_tot":8,"wait_cap":0,"wait_tot":0,"prereqs":null,"rmp":null},{"subject":"NURS","catalog_nbr":364,"section":612,"class_nbr":6366,"title":"NRSG","component":"CARE ADULTS I","units":0,"bldg":"TBA","room":"TBA","days":"M","time":"06","instructor":"Stone,ELIZABETH L","load":"100","rank":"INST","attributes":null,"enrl_cap":8,"enrl_tot":8,"wait_cap":0,"wait_tot":0,"prereqs":null,"rmp":null},{"subject":"NURS","catalog_nbr":364,"section":613,"class_nbr":16545,"title":"NRSG","component":"CARE ADULTS I","units":0,"bldg":"TBA","room":"TBA","days":"M","time":"07","instructor":"VALCHEFF,KAREN LOUISE","load":"100","rank":"INST","attributes":null,"enrl_cap":8,"enrl_tot":8,"wait_cap":0,"wait_tot":0,"prereqs":null,"rmp":null},{"subject":"NURS","catalog_nbr":364,"section":602,"class_nbr":6356,"title":"NRSG","component":"CARE ADULTS I","units":0,"bldg":"TBA","room":"TBA","days":"TuW","time":"07","instructor":"DAVIS,SUJA P","load":"100","rank":"INST","attributes":null,"enrl_cap":7,"enrl_tot":8,"wait_cap":0,"wait_tot":0,"prereqs":null,"rmp":{"url":"http://www.ratemyprofessors.com/ShowRatings.jsp?tid=1670073","fname":"Suja","lname":"Davis","quality":"0.0","easiness":"N/A","help":"N/A","clarity":"N/A","topTag":"","grade":"N/A","university":"University of North Carolina at Chapel Hill","chili":"cold","tags":[],"comments":[],"courses":[],"courseRatings":[]}}]