[{"subject":"NBIO","catalog_nbr":994,"section":6,"class_nbr":5655,"title":"DOCT RESEARCH AND DISSERTATIONLecture","component":"3","units":0,"bldg":"TBA","room":"TBA","days":"TBA","time":"TBA","instructor":"Staff","load":"100","rank":"PROX","attributes":null,"enrl_cap":5,"enrl_tot":0,"wait_cap":0,"wait_tot":0,"prereqs":null,"rmp":null},{"subject":"NBIO","catalog_nbr":994,"section":8,"class_nbr":5657,"title":"DOCT RESEARCH AND DISSERTATIONLecture","component":"3","units":0,"bldg":"TBA","room":"TBA","days":"TBA","time":"TBA","instructor":"Staff","load":"100","rank":"INST","attributes":null,"enrl_cap":5,"enrl_tot":0,"wait_cap":0,"wait_tot":0,"prereqs":null,"rmp":null},{"subject":"NBIO","catalog_nbr":994,"section":3,"class_nbr":5652,"title":"DOCT RESEARCH AND DISSERTATIONLecture","component":"3","units":0,"bldg":"TBA","room":"TBA","days":"TBA","time":"TBA","instructor":"Kenney,Denise E","load":"100","rank":"INST","attributes":null,"enrl_cap":5,"enrl_tot":1,"wait_cap":0,"wait_tot":0,"prereqs":null,"rmp":null},{"subject":"NBIO","catalog_nbr":994,"section":7,"class_nbr":5656,"title":"DOCT RESEARCH AND DISSERTATIONLecture","component":"3","units":0,"bldg":"TBA","room":"TBA","days":"TBA","time":"TBA","instructor":"Kenney,Denise E","load":"100","rank":"INST","attributes":null,"enrl_cap":5,"enrl_tot":1,"wait_cap":0,"wait_tot":0,"prereqs":null,"rmp":null},{"subject":"NBIO","catalog_nbr":994,"section":10,"class_nbr":5659,"title":"DOCT RESEARCH AND DISSERTATIONLecture","component":"3","units":0,"bldg":"TBA","room":"TBA","days":"TBA","time":"TBA","instructor":"SMITH,SPENCER L","load":"100","rank":"PROX","attributes":null,"enrl_cap":5,"enrl_tot":2,"wait_cap":0,"wait_tot":0,"prereqs":null,"rmp":null},{"subject":"NBIO","catalog_nbr":994,"section":16,"class_nbr":5670,"title":"DOCT RESEARCH AND DISSERTATIONLecture","component":"3","units":0,"bldg":"TBA","room":"TBA","days":"TBA","time":"TBA","instructor":"Staff","load":"100","rank":"PROX","attributes":null,"enrl_cap":5,"enrl_tot":0,"wait_cap":0,"wait_tot":0,"prereqs":null,"rmp":null},{"subject":"NBIO","catalog_nbr":994,"section":4,"class_nbr":5653,"title":"DOCT RESEARCH AND DISSERTATIONLecture","component":"3","units":0,"bldg":"TBA","room":"TBA","days":"TBA","time":"TBA","instructor":"HODGE,CLYDE W","load":"100","rank":"PROX","attributes":null,"enrl_cap":5,"enrl_tot":1,"wait_cap":0,"wait_tot":0,"prereqs":null,"rmp":null},{"subject":"NBIO","catalog_nbr":994,"section":18,"class_nbr":5672,"title":"DOCT RESEARCH AND DISSERTATIONLecture","component":"3","units":0,"bldg":"TBA","room":"TBA","days":"TBA","time":"TBA","instructor":"Staff","load":"100","rank":"PROX","attributes":null,"enrl_cap":5,"enrl_tot":0,"wait_cap":0,"wait_tot":0,"prereqs":null,"rmp":null},{"subject":"NBIO","catalog_nbr":994,"section":5,"class_nbr":5654,"title":"DOCT RESEARCH AND DISSERTATIONLecture","component":"3","units":0,"bldg":"TBA","room":"TBA","days":"TBA","time":"TBA","instructor":"DESHMUKH,MOHANISH P","load":"100","rank":"PROX","attributes":null,"enrl_cap":5,"enrl_tot":0,"wait_cap":0,"wait_tot":0,"prereqs":null,"rmp":null},{"subject":"NBIO","catalog_nbr":994,"section":11,"class_nbr":5660,"title":"DOCT RESEARCH AND DISSERTATIONLecture","component":"3","units":0,"bldg":"TBA","room":"TBA","days":"TBA","time":"TBA","instructor":"Kenney,Denise E","load":"100","rank":"INST","attributes":null,"enrl_cap":5,"enrl_tot":2,"wait_cap":0,"wait_tot":0,"prereqs":null,"rmp":null},{"subject":"NBIO","catalog_nbr":994,"section":2,"class_nbr":5651,"title":"DOCT RESEARCH AND DISSERTATIONLecture","component":"3","units":0,"bldg":"TBA","room":"TBA","days":"TBA","time":"TBA","instructor":"Neely,Andrea Gail","load":"100","rank":"PROX","attributes":null,"enrl_cap":5,"enrl_tot":0,"wait_cap":0,"wait_tot":0,"prereqs":null,"rmp":null},{"subject":"NBIO","catalog_nbr":994,"section":22,"class_nbr":5676,"title":"DOCT RESEARCH AND DISSERTATIONLecture","component":"3","units":0,"bldg":"TBA","room":"TBA","days":"TBA","time":"TBA","instructor":"Staff","load":"100","rank":"PROX","attributes":null,"enrl_cap":5,"enrl_tot":0,"wait_cap":0,"wait_tot":0,"prereqs":null,"rmp":null},{"subject":"NBIO","catalog_nbr":994,"section":1,"class_nbr":5650,"title":"DOCT RESEARCH AND DISSERTATIONLecture","component":"3","units":0,"bldg":"TBA","room":"TBA","days":"TBA","time":"TBA","instructor":"GUPTON,STEPHANIE LYNN","load":"100","rank":"PROX","attributes":null,"enrl_cap":5,"enrl_tot":1,"wait_cap":0,"wait_tot":0,"prereqs":null,"rmp":null},{"subject":"NBIO","catalog_nbr":994,"section":24,"class_nbr":5833,"title":"DOCT RESEARCH AND DISSERTATIONLecture","component":"3","units":0,"bldg":"TBA","room":"TBA","days":"TBA","time":"TBA","instructor":"Staff","load":"100","rank":"PROX","attributes":null,"enrl_cap":5,"enrl_tot":0,"wait_cap":0,"wait_tot":0,"prereqs":null,"rmp":null},{"subject":"NBIO","catalog_nbr":994,"section":27,"class_nbr":6117,"title":"DOCT RESEARCH AND DISSERTATIONLecture","component":"3","units":0,"bldg":"TBA","room":"TBA","days":"TBA","time":"TBA","instructor":"Staff","load":"100","rank":"PROX","attributes":null,"enrl_cap":5,"enrl_tot":0,"wait_cap":0,"wait_tot":0,"prereqs":null,"rmp":null},{"subject":"NBIO","catalog_nbr":994,"section":9,"class_nbr":5658,"title":"DOCT RESEARCH AND DISSERTATIONLecture","component":"3","units":0,"bldg":"TBA","room":"TBA","days":"TBA","time":"TBA","instructor":"ZYLKA,MARK J","load":"100","rank":"PROX","attributes":null,"enrl_cap":5,"enrl_tot":1,"wait_cap":0,"wait_tot":0,"prereqs":null,"rmp":null},{"subject":"NBIO","catalog_nbr":994,"section":29,"class_nbr":6118,"title":"DOCT RESEARCH AND DISSERTATIONLecture","component":"3","units":0,"bldg":"TBA","room":"TBA","days":"TBA","time":"TBA","instructor":"Staff","load":"100","rank":"PROX","attributes":null,"enrl_cap":5,"enrl_tot":0,"wait_cap":0,"wait_tot":0,"prereqs":null,"rmp":null},{"subject":"NBIO","catalog_nbr":994,"section":30,"class_nbr":6119,"title":"DOCT RESEARCH AND DISSERTATIONLecture","component":"3","units":0,"bldg":"TBA","room":"TBA","days":"TBA","time":"TBA","instructor":"Staff","load":"100","rank":"PROX","attributes":null,"enrl_cap":5,"enrl_tot":0,"wait_cap":0,"wait_tot":0,"prereqs":null,"rmp":null},{"subject":"NBIO","catalog_nbr":994,"section":12,"class_nbr":5661,"title":"DOCT RESEARCH AND DISSERTATIONLecture","component":"3","units":0,"bldg":"TBA","room":"TBA","days":"TBA","time":"TBA","instructor":"BESHEER,JOYCE","load":"100","rank":"PROX","attributes":null,"enrl_cap":5,"enrl_tot":1,"wait_cap":0,"wait_tot":0,"prereqs":null,"rmp":null},{"subject":"NBIO","catalog_nbr":994,"section":32,"class_nbr":6587,"title":"DOCT RESEARCH AND DISSERTATIONLecture","component":"3","units":0,"bldg":"TBA","room":"TBA","days":"TBA","time":"TBA","instructor":"Staff","load":"100","rank":"PROX","attributes":null,"enrl_cap":5,"enrl_tot":0,"wait_cap":0,"wait_tot":0,"prereqs":null,"rmp":null},{"subject":"NBIO","catalog_nbr":994,"section":14,"class_nbr":5663,"title":"DOCT RESEARCH AND DISSERTATIONLecture","component":"3","units":0,"bldg":"TBA","room":"TBA","days":"TBA","time":"TBA","instructor":"CREWS,FULTON T","load":"100","rank":"PROX","attributes":null,"enrl_cap":5,"enrl_tot":1,"wait_cap":0,"wait_tot":0,"prereqs":null,"rmp":null},{"subject":"NBIO","catalog_nbr":994,"section":13,"class_nbr":5662,"title":"DOCT RESEARCH AND DISSERTATIONLecture","component":"3","units":0,"bldg":"TBA","room":"TBA","days":"TBA","time":"TBA","instructor":"Santelli,REBECCA C","load":"100","rank":"PROX","attributes":null,"enrl_cap":5,"enrl_tot":1,"wait_cap":0,"wait_tot":0,"prereqs":null,"rmp":null},{"subject":"NBIO","catalog_nbr":994,"section":21,"class_nbr":5675,"title":"DOCT RESEARCH AND DISSERTATIONLecture","component":"3","units":0,"bldg":"TBA","room":"TBA","days":"TBA","time":"TBA","instructor":"KASH,THOMAS L.","load":"100","rank":"PROX","attributes":null,"enrl_cap":5,"enrl_tot":2,"wait_cap":0,"wait_tot":0,"prereqs":null,"rmp":null},{"subject":"NBIO","catalog_nbr":994,"section":17,"class_nbr":5671,"title":"DOCT RESEARCH AND DISSERTATIONLecture","component":"3","units":0,"bldg":"TBA","room":"TBA","days":"TBA","time":"TBA","instructor":"ROBINSON,DONITA L","load":"100","rank":"PROX","attributes":null,"enrl_cap":5,"enrl_tot":1,"wait_cap":0,"wait_tot":0,"prereqs":null,"rmp":null},{"subject":"NBIO","catalog_nbr":994,"section":23,"class_nbr":5832,"title":"DOCT RESEARCH AND DISSERTATIONLecture","component":"3","units":0,"bldg":"TBA","room":"TBA","days":"TBA","time":"TBA","instructor":"BELGER,AYSENIL","load":"100","rank":"PROX","attributes":null,"enrl_cap":5,"enrl_tot":1,"wait_cap":0,"wait_tot":0,"prereqs":null,"rmp":null},{"subject":"NBIO","catalog_nbr":994,"section":38,"class_nbr":7365,"title":"DOCT RESEARCH AND DISSERTATIONLecture","component":"3","units":0,"bldg":"TBA","room":"TBA","days":"TBA","time":"TBA","instructor":"Staff","load":"100","rank":"PROX","attributes":null,"enrl_cap":5,"enrl_tot":0,"wait_cap":0,"wait_tot":0,"prereqs":null,"rmp":null},{"subject":"NBIO","catalog_nbr":994,"section":40,"class_nbr":8286,"title":"DOCT RESEARCH AND DISSERTATIONLecture","component":"3","units":0,"bldg":"TBA","room":"TBA","days":"TBA","time":"TBA","instructor":"Staff","load":"100","rank":"PROX","attributes":null,"enrl_cap":5,"enrl_tot":0,"wait_cap":0,"wait_tot":0,"prereqs":null,"rmp":null},{"subject":"NBIO","catalog_nbr":994,"section":41,"class_nbr":8287,"title":"DOCT RESEARCH AND DISSERTATIONLecture","component":"3","units":0,"bldg":"TBA","room":"TBA","days":"TBA","time":"TBA","instructor":"Staff","load":"100","rank":"PROX","attributes":null,"enrl_cap":5,"enrl_tot":0,"wait_cap":0,"wait_tot":0,"prereqs":null,"rmp":null},{"subject":"NBIO","catalog_nbr":994,"section":42,"class_nbr":8288,"title":"DOCT RESEARCH AND DISSERTATIONLecture","component":"3","units":0,"bldg":"TBA","room":"TBA","days":"TBA","time":"TBA","instructor":"Staff","load":"100","rank":"PROX","attributes":null,"enrl_cap":5,"enrl_tot":0,"wait_cap":0,"wait_tot":0,"prereqs":null,"rmp":null},{"subject":"NBIO","catalog_nbr":994,"section":43,"class_nbr":8289,"title":"DOCT RESEARCH AND DISSERTATIONLecture","component":"3","units":0,"bldg":"TBA","room":"TBA","days":"TBA","time":"TBA","instructor":"Staff","load":"100","rank":"PROX","attributes":null,"enrl_cap":5,"enrl_tot":0,"wait_cap":0,"wait_tot":0,"prereqs":null,"rmp":null},{"subject":"NBIO","catalog_nbr":994,"section":19,"class_nbr":5673,"title":"DOCT RESEARCH AND DISSERTATIONLecture","component":"3","units":0,"bldg":"TBA","room":"TBA","days":"TBA","time":"TBA","instructor":"TARANTINO,LISA M","load":"100","rank":"PROX","attributes":null,"enrl_cap":5,"enrl_tot":1,"wait_cap":0,"wait_tot":0,"prereqs":null,"rmp":null},{"subject":"NBIO","catalog_nbr":994,"section":28,"class_nbr":5834,"title":"DOCT RESEARCH AND DISSERTATIONLecture","component":"3","units":0,"bldg":"TBA","room":"TBA","days":"TBA","time":"TBA","instructor":"SAMULSKI,RICHARD J","load":"100","rank":"PROX","attributes":null,"enrl_cap":5,"enrl_tot":1,"wait_cap":0,"wait_tot":0,"prereqs":null,"rmp":null},{"subject":"NBIO","catalog_nbr":994,"section":33,"class_nbr":6797,"title":"DOCT RESEARCH AND DISSERTATIONLecture","component":"3","units":0,"bldg":"TBA","room":"TBA","days":"TBA","time":"TBA","instructor":"GERSHON,TIMOTHY R","load":"100","rank":"PROX","attributes":null,"enrl_cap":5,"enrl_tot":2,"wait_cap":0,"wait_tot":0,"prereqs":null,"rmp":null},{"subject":"NBIO","catalog_nbr":994,"section":20,"class_nbr":5674,"title":"DOCT RESEARCH AND DISSERTATIONLecture","component":"3","units":0,"bldg":"TBA","room":"TBA","days":"TBA","time":"TBA","instructor":"GILMORE,JOHN H","load":"100","rank":"PROX","attributes":null,"enrl_cap":5,"enrl_tot":2,"wait_cap":0,"wait_tot":0,"prereqs":null,"rmp":null},{"subject":"NBIO","catalog_nbr":994,"section":31,"class_nbr":6586,"title":"DOCT RESEARCH AND DISSERTATIONLecture","component":"3","units":0,"bldg":"TBA","room":"TBA","days":"TBA","time":"TBA","instructor":"Song,Juan","load":"100","rank":"PROX","attributes":null,"enrl_cap":5,"enrl_tot":1,"wait_cap":0,"wait_tot":0,"prereqs":null,"rmp":null},{"subject":"NBIO","catalog_nbr":994,"section":35,"class_nbr":7362,"title":"DOCT RESEARCH AND DISSERTATIONLecture","component":"3","units":0,"bldg":"TBA","room":"TBA","days":"TBA","time":"TBA","instructor":"STUBER,GARRET D","load":"100","rank":"PROX","attributes":null,"enrl_cap":5,"enrl_tot":3,"wait_cap":0,"wait_tot":0,"prereqs":null,"rmp":null},{"subject":"NBIO","catalog_nbr":994,"section":34,"class_nbr":6814,"title":"DOCT RESEARCH AND DISSERTATIONLecture","component":"3","units":0,"bldg":"TBA","room":"TBA","days":"TBA","time":"TBA","instructor":"Dudek,Serena","load":"100","rank":"PROX","attributes":null,"enrl_cap":5,"enrl_tot":2,"wait_cap":0,"wait_tot":0,"prereqs":null,"rmp":null},{"subject":"NBIO","catalog_nbr":994,"section":36,"class_nbr":7363,"title":"DOCT RESEARCH AND DISSERTATIONLecture","component":"3","units":0,"bldg":"TBA","room":"TBA","days":"TBA","time":"TBA","instructor":"FROHLICH,FLAVIO","load":"100","rank":"PROX","attributes":null,"enrl_cap":5,"enrl_tot":1,"wait_cap":0,"wait_tot":0,"prereqs":null,"rmp":null},{"subject":"NBIO","catalog_nbr":994,"section":37,"class_nbr":7364,"title":"DOCT RESEARCH AND DISSERTATIONLecture","component":"3","units":0,"bldg":"TBA","room":"TBA","days":"TBA","time":"TBA","instructor":"SHIH,YEN-YU IAN","load":"100","rank":"PROX","attributes":null,"enrl_cap":5,"enrl_tot":2,"wait_cap":0,"wait_tot":0,"prereqs":null,"rmp":null}]