[{"subject":"MBA","catalog_nbr":804,"section":973,"class_nbr":16344,"title":"MGMT COMMUNICATION","component":"Lecture","units":1,"bldg":"TBA","room":"TBA","days":"Tu","time":"20","instructor":"SCHULTZ,HEIDI M","load":"100","rank":"INST","attributes":null,"enrl_cap":10,"enrl_tot":10,"wait_cap":0,"wait_tot":0,"prereqs":null,"rmp":{"url":"http://www.ratemyprofessors.com/ShowRatings.jsp?tid=1707252","fname":"Heidi","lname":"Schultz","quality":"0.0","easiness":"N/A","help":"N/A","clarity":"N/A","topTag":"","grade":"N/A","university":"University of North Carolina at Chapel Hill","chili":"cold","tags":[],"comments":[],"courses":[],"courseRatings":[]}}]