[{"subject":"ORTS","catalog_nbr":447,"section":1,"class_nbr":15756,"title":"ORTHO SUBSPEC, CMC","component":"Clinical","units":6,"bldg":"TBA","room":"TBA","days":"TBA","time":"TBA","instructor":"Staff","load":"100","rank":"PROX","attributes":null,"enrl_cap":999,"enrl_tot":0,"wait_cap":0,"wait_tot":0,"prereqs":null,"rmp":null},{"subject":"ORTS","catalog_nbr":447,"section":1,"class_nbr":15757,"title":"ORTHO SUBSPEC, CMC","component":"Clinical","units":6,"bldg":"TBA","room":"TBA","days":"TBA","time":"TBA","instructor":"Staff","load":"100","rank":"PROX","attributes":null,"enrl_cap":999,"enrl_tot":0,"wait_cap":0,"wait_tot":0,"prereqs":null,"rmp":null},{"subject":"ORTS","catalog_nbr":447,"section":1,"class_nbr":15758,"title":"ORTHO SUBSPEC, CMC","component":"Clinical","units":6,"bldg":"TBA","room":"TBA","days":"TBA","time":"TBA","instructor":"Staff","load":"100","rank":"PROX","attributes":null,"enrl_cap":999,"enrl_tot":0,"wait_cap":0,"wait_tot":0,"prereqs":null,"rmp":null},{"subject":"ORTS","catalog_nbr":447,"section":1,"class_nbr":15759,"title":"ORTHO SUBSPEC, CMC","component":"Clinical","units":6,"bldg":"TBA","room":"TBA","days":"TBA","time":"TBA","instructor":"Staff","load":"100","rank":"PROX","attributes":null,"enrl_cap":999,"enrl_tot":0,"wait_cap":0,"wait_tot":0,"prereqs":null,"rmp":null},{"subject":"ORTS","catalog_nbr":447,"section":1,"class_nbr":15760,"title":"ORTHO SUBSPEC, CMC","component":"Clinical","units":6,"bldg":"TBA","room":"TBA","days":"TBA","time":"TBA","instructor":"Staff","load":"100","rank":"PROX","attributes":null,"enrl_cap":999,"enrl_tot":0,"wait_cap":0,"wait_tot":0,"prereqs":null,"rmp":null},{"subject":"ORTS","catalog_nbr":447,"section":1,"class_nbr":15761,"title":"ORTHO SUBSPEC, CMC","component":"Clinical","units":6,"bldg":"TBA","room":"TBA","days":"TBA","time":"TBA","instructor":"Staff","load":"100","rank":"PROX","attributes":null,"enrl_cap":999,"enrl_tot":0,"wait_cap":0,"wait_tot":0,"prereqs":null,"rmp":null}]