[{"subject":"BIOL","catalog_nbr":221,"section":401,"class_nbr":13890,"title":"FOOD MISLABELING LAB","component":"Lab","units":1,"bldg":"Coker","room":"0214","days":"W","time":"13","instructor":"BRUNO,JOHN F","load":"50","rank":"INST","attributes":null,"enrl_cap":20,"enrl_tot":16,"wait_cap":5,"wait_tot":0,"prereqs":null,"rmp":{"url":"http://www.ratemyprofessors.com/ShowRatings.jsp?tid=1280920","fname":"John","lname":"Bruno","quality":"5.0","easiness":"1.5","help":"1.5","clarity":"1.5","topTag":"","grade":"1.5","university":"University of North Carolina at Chapel Hill","chili":"cold","tags":[],"comments":["Bruno is awesome! Super chill guy, great professor, and his class isn't very hard. Do the basics and you'll be fine.","Loved him"],"courses":["BIOL462","MASC404"],"courseRatings":["AWESOME","AWESOME"]}},{"subject":"BIOL","catalog_nbr":221,"section":1,"class_nbr":13888,"title":"FOOD MISLABEL AND HUMAN HEALTHLecture","component":"3","units":0,"bldg":"Coker","room":"0214","days":"W","time":"12","instructor":"BRUNO,JOHN F","load":"50","rank":"INST","attributes":null,"enrl_cap":20,"enrl_tot":16,"wait_cap":5,"wait_tot":0,"prereqs":null,"rmp":{"url":"http://www.ratemyprofessors.com/ShowRatings.jsp?tid=1280920","fname":"John","lname":"Bruno","quality":"5.0","easiness":"1.5","help":"1.5","clarity":"1.5","topTag":"","grade":"1.5","university":"University of North Carolina at Chapel Hill","chili":"cold","tags":[],"comments":["Bruno is awesome! Super chill guy, great professor, and his class isn't very hard. Do the basics and you'll be fine.","Loved him"],"courses":["BIOL462","MASC404"],"courseRatings":["AWESOME","AWESOME"]}}]